[{ "code": 0, "length": 10, "reward": -100, "trajectories": [[[0, 7],[1, 7],[1, 6],[1, 5],[1, 4],[1, 3],[1, 2],[1, 1],[1, 0],[2, 0],[2, -1]],[[-7, 7],[-6, 7],[-4, 7],[-2, 7],[0, 7],[1, 7],[1, 5],[1, 3],[1, 1],[2, 1],[2, -1]]], "estimated_rewards": [ -15.5556, -1.91083, -18.7166, -40.6977, -59.3023, -46.1538, -52.5424, -90, -88.7324, -92.0904]},{ "code": 1, "length": 18, "reward": 100, "trajectories": [[[0, 7],[1, 7],[1, 6],[1, 5],[1, 4],[1, 3],[1, 2],[1, 1],[1, 0],[2, 0],[2, -1],[2, -2],[2, -3],[2, -4],[1, -4],[1, -5],[1, -6],[0, -6],[0, -7]],[[-7, 7],[-6, 7],[-5, 7],[-3, 7],[-1, 7],[1, 7],[1, 6],[1, 5],[0, 5],[2, 5],[2, 4],[2, 3],[2, 2],[2, 1],[2, -1],[2, -2],[2, -4],[1, -5],[0, -5]]], "estimated_rewards": [ -15.6069, 4.65116, 17.7083, 2.7933, -27.1605, -41.8182, -25.2874, 6.50888, 90.303, 74.7253, 88.9447, 96.1783, 100, 100, 100, 100, 100, 100]},{ "code": 0, "length": 9, "reward": -100, "trajectories": [[[0, 7],[1, 7],[1, 6],[1, 5],[1, 4],[1, 3],[1, 2],[1, 1],[1, 0],[2, 0]],[[-7, 7],[-5, 7],[-3, 7],[-1, 7],[0, 7],[1, 6],[1, 5],[1, 3],[1, 1],[2, 0]]], "estimated_rewards": [ -19.3182, -39.1304, -49.4505, -65.0602, -58.3815, -70.8108, -63.5294, -80.117, -95.122]},{ "code": 0, "length": 11, "reward": -100, "trajectories": [[[0, 7],[1, 7],[1, 6],[1, 5],[1, 4],[1, 3],[1, 2],[1, 1],[1, 0],[2, 0],[2, -1],[2, -2]],[[-7, 7],[-6, 7],[-5, 7],[-4, 7],[-2, 7],[0, 7],[1, 7],[1, 5],[1, 3],[2, 2],[2, 0],[2, -2]]], "estimated_rewards": [ -13.0952, -6.58683, 22.2857, 30.6358, 18.5185, -2.73973, 15, 13.0435, -27.381, -55.2795, -68.1529]},{ "code": 0, "length": 13, "reward": -100, "trajectories": [[[0, 7],[1, 7],[1, 6],[1, 5],[1, 4],[1, 3],[1, 2],[1, 1],[1, 0],[2, 0],[2, -1],[2, -2],[2, -3],[2, -4]],[[-7, 7],[-5, 7],[-3, 7],[-2, 7],[-1, 7],[1, 7],[1, 5],[1, 4],[1, 3],[2, 2],[2, 1],[2, 0],[2, -2],[2, -4]]], "estimated_rewards": [ -29.1429, -43.299, -63.0952, -31.7073, -31.25, -31.2102, -65.9341, -52.7473, -40.3315, -62.3656, -30.9091, 3.8961, -34.8315]},{ "code": 0, "length": 12, "reward": -100, "trajectories": [[[0, 7],[1, 7],[1, 6],[1, 5],[1, 4],[1, 3],[1, 2],[1, 1],[1, 0],[2, 0],[2, -1],[2, -2],[2, -3]],[[-7, 7],[-5, 7],[-3, 7],[-1, 7],[0, 7],[1, 7],[1, 5],[1, 4],[1, 3],[2, 3],[2, 1],[2, -1],[2, -3]]], "estimated_rewards": [ -21.2903, -22.619, -54.9133, -69.8113, -60.7362, -43.8202, -66.0606, -57.8947, -30.2326, -6.95187, -27.9503, -77.6316]},{ "code": 0, "length": 11, "reward": -100, "trajectories": [[[0, 7],[1, 7],[1, 6],[1, 5],[1, 4],[1, 3],[1, 2],[1, 1],[1, 0],[2, 0],[2, -1],[2, -2]],[[-7, 7],[-6, 7],[-4, 7],[-3, 7],[-1, 7],[1, 7],[1, 5],[1, 4],[1, 3],[2, 2],[2, 0],[2, -2]]], "estimated_rewards": [ -19.7917, -4.65116, -10.1266, 1.79641, -24, -46.6667, -62.963, -49.1525, -28, -49.7268, -86.2069]},{ "code": 0, "length": 13, "reward": -100, "trajectories": [[[0, 7],[1, 7],[1, 6],[1, 5],[1, 4],[1, 3],[1, 2],[1, 1],[1, 0],[2, 0],[2, -1],[2, -2],[2, -3],[2, -4]],[[-7, 7],[-5, 7],[-4, 7],[-3, 7],[-1, 7],[-1, 6],[1, 6],[1, 4],[1, 2],[2, 1],[2, 0],[2, -1],[2, -2],[2, -4]]], "estimated_rewards": [ -22.7273, -33.7209, -13.9073, -2.29885, -23.7113, -7.34463, -26.7081, -47.541, -72.619, -87.9518, -74.1935, -64.5714, -36.1446]},{ "code": 1, "length": 18, "reward": 100, "trajectories": [[[0, 7],[1, 7],[1, 6],[1, 5],[1, 4],[1, 3],[1, 2],[1, 1],[1, 0],[2, 0],[2, -1],[2, -2],[2, -3],[2, -4],[1, -4],[1, -5],[1, -6],[0, -6],[0, -7]],[[-7, 7],[-6, 7],[-4, 7],[-3, 7],[-1, 7],[0, 7],[1, 6],[1, 5],[1, 3],[2, 2],[2, 1],[1, 1],[2, 1],[2, 0],[2, -1],[2, -2],[2, -4],[0, -4],[0, -5]]], "estimated_rewards": [ -9.89011, 5.68182, -13.0952, 7.87879, -28.75, -8.07453, -25.4438, -2.1978, -22.9814, -56.0694, -41.6149, 87.7095, 89.1156, 100, 100, 100, 100, 100]},{ "code": 0, "length": 7, "reward": -100, "trajectories": [[[0, 7],[1, 7],[1, 6],[1, 5],[1, 4],[1, 3],[1, 2],[1, 1]],[[-7, 7],[-5, 7],[-3, 7],[-1, 7],[1, 7],[1, 5],[1, 3],[1, 1]]], "estimated_rewards": [ -4.97238, -37.5796, -60.2564, -67.4157, -86.6667, -93.3333, -98.8235]}]