[{ "winner": 0, "length": 24, "reward": 100, "trajectories": [[[0, 7],[-1, 7],[-2, 7],[-3, 7],[-3, 6],[-3, 5],[-3, 4],[-3, 3],[-3, 2],[-3, 1],[-3, 0],[-3, -1],[-4, -1],[-3, -1],[-4, -1],[-4, -2],[-4, -3],[-4, -4],[-4, -5],[-4, -6],[-4, -7],[-3, -7],[-2, -7],[-1, -7],[0, -7]],[[6, 2],[5, 2],[5, 0],[5, -2],[4, -2],[2, -2],[1, -2],[0, -2],[-1, -2],[-1, -3],[-2, -4],[-3, -4],[-4, -4],[-3, -4],[-1, -4],[0, -4],[2, -4],[1, -4],[0, -4],[-1, -4],[-3, -4],[-3, -6],[-2, -6],[-1, -6],[0, -7]]], "estimated_rewards": [ -90.4255, -94.2529, -88.8372, -82.3204, -83.6735, -85.7923, -76.9634, -80.4348, -63.7427, -75.8242, -70.1357, -71.4286, -95.6757, -84.2105, -86.0465, -78.3251, -92.0398, -84.0909, -35.9551, 36.7816, 14.4279, -43.1818, 8.98204, 100]},{ "winner": 1, "length": 16, "reward": -100, "trajectories": [[[0, 7],[-1, 7],[-2, 7],[-3, 7],[-3, 6],[-3, 5],[-3, 4],[-3, 3],[-3, 2],[-3, 1],[-3, 0],[-3, -1],[-4, -1],[-3, -1],[-4, -1],[-3, -1],[-4, -1]],[[6, 2],[5, 2],[5, 0],[5, -1],[5, -2],[3, -2],[2, -2],[0, -2],[-1, -2],[-1, -3],[-1, -4],[-3, -4],[-5, -4],[-4, -4],[-4, -3],[-4, -2],[-4, -1]]], "estimated_rewards": [ -89.5833, -86.6667, -86.5285, -81.2155, -88.5714, -81.7143, -81.6425, -79.8942, -75.8242, -72.1854, -72.1393, -80.198, -95.3216, -90.7216, -96.3855, -91.9192]},{ "winner": 1, "length": 27, "reward": -100, "trajectories": [[[0, 7],[-1, 7],[-2, 7],[-2, 6],[-3, 6],[-3, 5],[-3, 4],[-3, 3],[-3, 2],[-3, 1],[-3, 0],[-3, -1],[-4, -1],[-4, 0],[-3, 0],[-3, -1],[-4, -1],[-4, -2],[-4, -1],[-4, -2],[-4, -3],[-4, -4],[-4, -5],[-4, -6],[-4, -7],[-3, -7],[-2, -7],[-1, -7]],[[6, 2],[5, 2],[5, 1],[5, -1],[5, -2],[4, -2],[2, -2],[1, -2],[0, -2],[-1, -2],[-1, -4],[-3, -4],[-5, -4],[-4, -4],[-3, -4],[-1, -4],[-2, -4],[-3, -4],[-2, -4],[0, -4],[1, -4],[-1, -4],[-3, -4],[-4, -4],[-4, -6],[-3, -6],[-2, -6],[-1, -7]]], "estimated_rewards": [ -94.0299, -91.8129, -95.5801, -87.7551, -75.8242, -84.5411, -82, -73.7374, -67.1958, -73.0337, -67.2131, -82.0225, -97.4359, -97.235, -72.8507, -81.1881, -81.7143, -95.8974, -80.2198, -87.2549, -91.0615, -94.9495, -63.9535, -37.3737, -68.4211, -45.7627, 7.53769]},{ "winner": 1, "length": 20, "reward": -100, "trajectories": [[[0, 7],[-1, 7],[-2, 7],[-3, 7],[-3, 6],[-3, 5],[-3, 4],[-3, 3],[-3, 2],[-3, 1],[-3, 0],[-3, -1],[-4, -1],[-3, -1],[-4, -1],[-4, -2],[-4, -3],[-4, -2],[-4, -1],[-3, -1],[-4, -1]],[[6, 2],[5, 1],[5, -1],[5, -2],[3, -2],[2, -2],[1, -2],[0, -2],[-1, -3],[-2, -4],[-3, -4],[-5, -4],[-4, -3],[-3, -4],[-2, -4],[-1, -3],[-2, -4],[-4, -4],[-4, -3],[-4, -1],[-4, -1]]], "estimated_rewards": [ -85.3659, -94.8718, -91.2088, -85.8824, -88.1188, -85.0267, -79.235, -76.7956, -82.659, -72.619, -81.1518, -79.3103, -98.8235, -89.7436, -88.0435, -89.8305, -96.7391, -94.2029, -95.7447, -99.0099]},{ "winner": 1, "length": 12, "reward": -100, "trajectories": [[[0, 7],[-1, 7],[-2, 7],[-3, 7],[-3, 6],[-3, 5],[-3, 4],[-3, 3],[-3, 2],[-3, 1],[-3, 0],[-3, -1],[-4, -1]],[[6, 2],[5, 1],[5, 0],[5, -2],[3, -2],[1, -2],[0, -2],[-1, -2],[-1, -4],[-2, -4],[-3, -4],[-4, -3],[-4, -1]]], "estimated_rewards": [ -90.6542, -91.2088, -82.1229, -78.9474, -92.4731, -88.4211, -73.3333, -83.3333, -77.2727, -82.5641, -76.8844, -72.8643]},{ "winner": 1, "length": 26, "reward": -100, "trajectories": [[[0, 7],[-1, 7],[-2, 7],[-3, 7],[-3, 6],[-3, 5],[-3, 4],[-3, 3],[-3, 2],[-3, 1],[-3, 0],[-3, -1],[-4, -1],[-4, -2],[-4, -1],[-3, -1],[-3, 0],[-3, -1],[-4, -1],[-4, -2],[-4, -3],[-4, -4],[-4, -5],[-4, -6],[-4, -7],[-3, -7],[-2, -7]],[[6, 2],[5, 2],[5, 1],[5, -1],[4, -2],[5, -1],[4, -2],[3, -2],[1, -2],[0, -2],[-1, -2],[-1, -4],[-2, -4],[-4, -4],[-4, -2],[-4, -3],[-3, -4],[-2, -4],[0, -4],[2, -4],[3, -4],[1, -4],[-1, -4],[-3, -4],[-4, -5],[-3, -6],[-2, -7]]], "estimated_rewards": [ -92.8205, -82.6087, -91.5152, -80.4348, -86.4583, -76.3547, -78.5311, -76.3314, -70.6215, -76.3441, -78.6802, -78.3019, -74.8691, -94.0887, -94.9495, -95.098, -77.0833, -83.871, -74.359, -87, -89.1566, -82.7957, -57.1429, 45, 16.0221, -45.4545]},{ "winner": 1, "length": 25, "reward": -100, "trajectories": [[[0, 7],[-1, 7],[-2, 7],[-3, 7],[-3, 6],[-3, 5],[-3, 4],[-3, 3],[-3, 2],[-3, 1],[-3, 0],[-3, -1],[-4, -1],[-4, -2],[-4, -1],[-3, -1],[-4, -1],[-4, -2],[-4, -1],[-3, -1],[-4, -1],[-4, -2],[-4, -1],[-3, -1],[-3, 0],[-3, -1]],[[6, 2],[5, 2],[5, 1],[5, 0],[5, -1],[5, -2],[4, -2],[3, -2],[1, -2],[-1, -2],[-1, -3],[-1, -4],[-2, -4],[-4, -4],[-4, -3],[-3, -3],[-3, -4],[-4, -3],[-4, -2],[-3, -3],[-3, -4],[-4, -4],[-4, -2],[-4, -1],[-3, -1],[-3, -1]]], "estimated_rewards": [ -84.8485, -90.2439, -91.411, -84.9246, -77.0925, -82.1656, -75.419, -84.6995, -70.3704, -66.6667, -65.445, -82.6531, -80.4598, -96.0976, -94.2857, -82.7586, -87.0968, -97.7901, -93.617, -93.8596, -91.2568, -96.6102, -95.4802, -100, -100]},{ "winner": 1, "length": 17, "reward": -100, "trajectories": [[[0, 7],[-1, 7],[-2, 7],[-3, 7],[-3, 6],[-3, 5],[-3, 4],[-3, 3],[-3, 2],[-3, 1],[-3, 0],[-3, -1],[-4, -1],[-4, -2],[-4, -3],[-4, -2],[-4, -1],[-3, -1]],[[6, 2],[5, 1],[5, -1],[4, -2],[5, -1],[5, 0],[5, 2],[5, 1],[5, -1],[5, -2],[3, -2],[1, -2],[-1, -2],[-1, -4],[-3, -4],[-4, -3],[-4, -2],[-3, -1]]], "estimated_rewards": [ -89.2473, -89.8305, -89.3617, -84.9462, -84.2365, -83.0986, -72.6708, -77.0115, -77.5, -71.5736, -77.2973, -77.7778, -69.4915, -55.4286, -94.7917, -96.7033, -96.9543]},{ "winner": 1, "length": 22, "reward": -100, "trajectories": [[[0, 7],[-1, 7],[-2, 7],[-3, 7],[-3, 6],[-3, 5],[-3, 4],[-3, 3],[-3, 2],[-3, 1],[-3, 0],[-3, -1],[-4, -1],[-4, -2],[-4, -1],[-3, -1],[-4, -1],[-4, -2],[-4, -3],[-4, -2],[-4, -1],[-3, -1],[-4, -1]],[[6, 2],[5, 2],[5, 1],[5, -1],[4, -2],[3, -2],[2, -2],[0, -2],[-1, -3],[-2, -4],[-4, -4],[-2, -4],[-3, -4],[-4, -4],[-4, -3],[-3, -4],[-2, -4],[-1, -4],[-2, -4],[-4, -4],[-4, -3],[-4, -1],[-4, -1]]], "estimated_rewards": [ -87.5, -90.4306, -93.0233, -89.5833, -85.5556, -83.8863, -88.2353, -83.5052, -78.7234, -70.6806, -70.4082, -80.8511, -70.8108, -95.9596, -93.6306, -87.6923, -83.1461, -83.1579, -94.186, -97.9275, -96.7213, -100]},{ "winner": 0, "length": 22, "reward": 100, "trajectories": [[[0, 7],[-1, 7],[-2, 7],[-3, 7],[-3, 6],[-3, 5],[-3, 4],[-3, 3],[-3, 2],[-3, 1],[-3, 0],[-3, -1],[-4, -1],[-4, -2],[-4, -3],[-4, -4],[-4, -5],[-4, -6],[-4, -7],[-3, -7],[-2, -7],[-1, -7],[0, -7]],[[6, 2],[5, 1],[5, 0],[5, -1],[5, -2],[5, -1],[5, 0],[5, 1],[4, 2],[2, 2],[3, 2],[4, 2],[5, 2],[5, 0],[5, -2],[4, -2],[2, -2],[0, -2],[-1, -2],[-1, -4],[-2, -5],[-1, -6],[-2, -6]]], "estimated_rewards": [ -87.2832, -92.4528, -89.4737, -88.172, -77.4359, -83, -75.5556, -74.1935, -82.6087, -78.3505, -72.7749, -78.8235, -78.4615, -71.4286, -50, 3.15789, 5.82011, 91.2088, 100, 100, 100, 100]},{ "winner": 1, "length": 21, "reward": -100, "trajectories": [[[0, 7],[-1, 7],[-2, 7],[-3, 7],[-3, 6],[-3, 5],[-3, 4],[-3, 3],[-3, 2],[-3, 1],[-3, 0],[-3, -1],[-4, -1],[-4, -2],[-4, -3],[-4, -4],[-4, -5],[-4, -6],[-4, -7],[-3, -7],[-2, -7],[-1, -7]],[[6, 2],[7, 2],[5, 2],[5, 1],[5, 0],[5, -2],[3, -2],[1, -2],[0, -2],[-1, -3],[-1, -4],[0, -4],[2, -4],[4, -4],[3, -4],[2, -4],[0, -4],[-2, -4],[-3, -4],[-3, -5],[-2, -6],[-1, -7]]], "estimated_rewards": [ -91.0448, -93.8272, -84.2105, -80.7107, -85.5856, -90.1639, -77.6471, -74.4898, -78.0347, -76.2712, -63.9535, -71.2707, -74.8503, -59.1837, -49.7006, -82.1053, -35.4839, 40.3727, 10, 56.383, 10.4972]},{ "winner": 0, "length": 22, "reward": 100, "trajectories": [[[0, 7],[-1, 7],[-2, 7],[-3, 7],[-3, 6],[-3, 5],[-3, 4],[-3, 3],[-3, 2],[-3, 1],[-3, 0],[-3, -1],[-4, -1],[-4, -2],[-4, -3],[-4, -4],[-4, -5],[-4, -6],[-4, -7],[-3, -7],[-2, -7],[-1, -7],[0, -7]],[[6, 2],[5, 2],[5, 1],[5, -1],[5, -2],[4, -2],[2, -2],[1, -2],[-1, -2],[-1, -4],[-2, -4],[-3, -4],[-2, -4],[0, -4],[2, -4],[1, -4],[-1, -4],[-2, -4],[-4, -4],[-3, -4],[-2, -4],[-1, -4],[0, -5]]], "estimated_rewards": [ -90.3226, -89.8618, -88.2353, -90.6736, -83.1111, -80.6122, -80.2326, -77.7778, -78.4038, -68.2353, -68.6869, -78.7879, -65.625, -67.5676, -56.5217, -89.4737, -58.5106, 37.6344, 85.1429, 100, 100, 100]},{ "winner": 0, "length": 22, "reward": 100, "trajectories": [[[0, 7],[-1, 7],[-2, 7],[-2, 6],[-3, 6],[-3, 5],[-3, 4],[-3, 3],[-3, 2],[-3, 1],[-3, 0],[-3, -1],[-4, -1],[-4, -2],[-4, -3],[-4, -4],[-4, -5],[-4, -6],[-4, -7],[-3, -7],[-2, -7],[-1, -7],[0, -7]],[[6, 2],[5, 1],[5, 0],[5, -1],[5, -2],[3, -2],[1, -2],[-1, -2],[-1, -3],[-1, -4],[-2, -4],[-3, -4],[-2, -4],[0, -4],[2, -4],[1, -4],[-1, -4],[-3, -4],[-4, -4],[-3, -5],[-2, -5],[-1, -5],[0, -6]]], "estimated_rewards": [ -88.2979, -89.6907, -88.3721, -84.4444, -90.6103, -74.5098, -81.1518, -79.8742, -71.7514, -71.1443, -69.6629, -70.6522, -75.2809, -58.8785, -53.2164, -74.1935, -65.6863, 41.8605, 81.4208, 60.4396, 100, 100]},{ "winner": 1, "length": 31, "reward": -100, "trajectories": [[[0, 7],[-1, 7],[-2, 7],[-3, 7],[-3, 6],[-3, 5],[-3, 4],[-3, 3],[-3, 2],[-3, 1],[-3, 0],[-3, -1],[-4, -1],[-4, -2],[-4, -1],[-3, -1],[-4, -1],[-4, -2],[-4, -1],[-4, 0],[-3, 0],[-3, -1],[-4, -1],[-4, -2],[-4, -3],[-4, -4],[-4, -5],[-4, -6],[-4, -7],[-3, -7],[-2, -7],[-1, -7]],[[6, 2],[5, 2],[5, 1],[5, -1],[5, -2],[3, -2],[2, -2],[1, -2],[0, -2],[-1, -2],[-1, -3],[-1, -4],[-2, -4],[-3, -4],[-4, -3],[-3, -3],[-2, -4],[-3, -4],[-4, -4],[-4, -3],[-3, -4],[-1, -4],[0, -4],[1, -4],[3, -4],[1, -4],[0, -4],[-1, -4],[-3, -4],[-3, -6],[-2, -6],[-1, -7]]], "estimated_rewards": [ -92.233, -92.8144, -89.011, -82.0896, -82.5641, -83.0303, -77.4648, -69.8925, -72.1925, -66.3265, -79.6296, -73.3333, -76.7196, -94.5355, -97.4359, -91.6667, -85.567, -92.6316, -96.7033, -98.8701, -82.439, -84.7826, -85.7988, -86.8263, -89, -92.5532, -39.3035, 32.5967, 15.5556, -44.6328, -6.3869e-16]},{ "winner": 1, "length": 15, "reward": -100, "trajectories": [[[0, 7],[-1, 7],[-2, 7],[-3, 7],[-3, 6],[-3, 5],[-3, 4],[-3, 3],[-3, 2],[-3, 1],[-3, 0],[-3, -1],[-4, -1],[-3, -1],[-3, 0],[-3, -1]],[[6, 2],[5, 1],[5, 0],[5, -1],[5, -2],[4, -2],[3, -2],[1, -2],[-1, -2],[-1, -4],[-2, -4],[-4, -4],[-4, -3],[-4, -1],[-3, -1],[-3, -1]]], "estimated_rewards": [ -91.3043, -88.2353, -91.2568, -90.1478, -90.7216, -80.3109, -82.1656, -81.9277, -70.7317, -76.4103, -77.665, -76.1658, -95.6757, -100, -100]},{ "winner": 1, "length": 16, "reward": -100, "trajectories": [[[0, 7],[-1, 7],[-2, 7],[-2, 6],[-3, 6],[-3, 5],[-3, 4],[-3, 3],[-3, 2],[-3, 1],[-3, 0],[-3, -1],[-4, -1],[-4, -2],[-4, -1],[-3, -1],[-4, -1]],[[6, 2],[5, 1],[5, 0],[5, -2],[4, -2],[2, -2],[1, -2],[-1, -2],[-1, -4],[-3, -4],[-4, -4],[-2, -4],[-1, -4],[-3, -4],[-4, -4],[-4, -2],[-4, -1]]], "estimated_rewards": [ -91.7526, -84.2932, -88.9503, -91.5344, -82.8571, -83.8095, -71.9101, -78, -79.0123, -74.5856, -68.8172, -74.0113, -73.5849, -95.7895, -96.8421, -86.0963]},{ "winner": 1, "length": 12, "reward": -100, "trajectories": [[[0, 7],[-1, 7],[-2, 7],[-3, 7],[-3, 6],[-3, 5],[-3, 4],[-3, 3],[-3, 2],[-3, 1],[-3, 0],[-3, -1],[-4, -1]],[[6, 2],[5, 1],[5, -1],[5, -2],[4, -2],[2, -2],[1, -2],[-1, -2],[-1, -4],[-3, -4],[-4, -4],[-4, -2],[-4, -1]]], "estimated_rewards": [ -90.3846, -92.1348, -89.7959, -82.9146, -85.3659, -73.7143, -83.2402, -78.6096, -72.043, -70.9497, -81.6092, -74.0541]},{ "winner": 1, "length": 12, "reward": -100, "trajectories": [[[0, 7],[-1, 7],[-2, 7],[-3, 7],[-3, 6],[-3, 5],[-3, 4],[-3, 3],[-3, 2],[-3, 1],[-3, 0],[-3, -1],[-4, -1]],[[6, 2],[5, 1],[5, 0],[5, -1],[5, -2],[3, -2],[1, -2],[0, -2],[-1, -3],[-2, -4],[-4, -4],[-4, -2],[-4, -1]]], "estimated_rewards": [ -88.6792, -85.1429, -93.75, -85.7988, -90.625, -78.2609, -74.4444, -74.5283, -69.8795, -77.5401, -76.2887, -73.0337]},{ "winner": 0, "length": 22, "reward": 100, "trajectories": [[[0, 7],[-1, 7],[-2, 7],[-3, 7],[-3, 6],[-3, 5],[-3, 4],[-3, 3],[-3, 2],[-3, 1],[-3, 0],[-3, -1],[-4, -1],[-4, -2],[-4, -3],[-4, -4],[-4, -5],[-4, -6],[-4, -7],[-3, -7],[-2, -7],[-1, -7],[0, -7]],[[6, 2],[5, 2],[5, 0],[5, -2],[4, -2],[3, -2],[1, -2],[0, -2],[-1, -3],[-2, -4],[-1, -4],[1, -4],[3, -4],[4, -4],[5, -4],[4, -4],[2, -4],[0, -4],[-1, -4],[-2, -4],[-2, -5],[-1, -6],[0, -7]]], "estimated_rewards": [ -88.7755, -87.3418, -91.2568, -80.7487, -87.6923, -85.4749, -76.9697, -82.0896, -75.9563, -69.7674, -73.8739, -77, -70, -61.7284, -59.5506, -70.6806, -15.3439, 77.3196, 85.1852, 60.7595, 100, 100]},{ "winner": 0, "length": 22, "reward": 100, "trajectories": [[[0, 7],[-1, 7],[-2, 7],[-3, 7],[-3, 6],[-3, 5],[-3, 4],[-3, 3],[-3, 2],[-3, 1],[-3, 0],[-3, -1],[-4, -1],[-4, -2],[-4, -3],[-4, -4],[-4, -5],[-4, -6],[-4, -7],[-3, -7],[-2, -7],[-1, -7],[0, -7]],[[6, 2],[5, 1],[5, -1],[4, -2],[2, -2],[4, -2],[5, -1],[5, 0],[5, 2],[5, 1],[5, 0],[5, -1],[5, -2],[5, -1],[5, 0],[5, 1],[5, -1],[5, -2],[4, -2],[2, -2],[0, -2],[-1, -2],[0, -2]]], "estimated_rewards": [ -91.2195, -96.4497, -82.8877, -75.1479, -89.2683, -82.6087, -80.117, -80.791, -76.2162, -70.9677, -80.2083, -76.2887, -70.9677, -66.8449, -60.6383, 10.1796, 27.8689, 100, 100, 100, 100, 100]},{ "winner": 1, "length": 16, "reward": -100, "trajectories": [[[0, 7],[-1, 7],[-2, 7],[-3, 7],[-3, 6],[-3, 5],[-4, 5],[-4, 4],[-4, 3],[-4, 2],[-4, 1],[-4, 0],[-4, -1],[-3, -1],[-4, -1],[-3, -1],[-4, -1]],[[6, 2],[5, 1],[5, -1],[5, -2],[3, -2],[2, -2],[1, -2],[-1, -2],[-1, -4],[-2, -4],[-1, -4],[-3, -4],[-4, -3],[-3, -3],[-4, -3],[-4, -1],[-4, -1]]], "estimated_rewards": [ -88.9447, -88.8325, -87.1658, -81.9149, -85.7988, -87.2611, -78.6802, -77.5401, -68.3673, -69.8925, -75.9162, -78.0488, -96.5714, -91.2195, -97.7778, -100]},{ "winner": 0, "length": 22, "reward": 100, "trajectories": [[[0, 7],[-1, 7],[-2, 7],[-3, 7],[-3, 6],[-3, 5],[-3, 4],[-3, 3],[-3, 2],[-3, 1],[-3, 0],[-3, -1],[-4, -1],[-4, -2],[-4, -3],[-4, -4],[-4, -5],[-4, -6],[-4, -7],[-3, -7],[-2, -7],[-1, -7],[0, -7]],[[6, 2],[5, 1],[5, 0],[5, -2],[3, -2],[1, -2],[-1, -2],[-1, -4],[-2, -4],[-4, -4],[-2, -4],[-1, -4],[1, -4],[3, -4],[5, -4],[3, -4],[2, -4],[1, -4],[-1, -4],[-3, -4],[-2, -5],[-1, -6],[0, -7]]], "estimated_rewards": [ -91.4439, -89.071, -93.1034, -88.0435, -86.1272, -79.2079, -78.4946, -72.5888, -71.0843, -70.9497, -72.2543, -71.9457, -72.2892, -59.6059, -65.5914, -81.0651, -8.02139, 71.5686, 84.8837, 100, 100, 100]},{ "winner": 1, "length": 20, "reward": -100, "trajectories": [[[0, 7],[-1, 7],[-2, 7],[-3, 7],[-3, 6],[-3, 5],[-3, 4],[-3, 3],[-3, 2],[-3, 1],[-3, 0],[-3, -1],[-4, -1],[-4, -2],[-4, -3],[-4, -4],[-4, -5],[-4, -6],[-4, -7],[-3, -7],[-2, -7]],[[6, 2],[5, 1],[5, 0],[5, -1],[4, -2],[3, -2],[1, -2],[-1, -2],[-1, -3],[-2, -4],[-4, -4],[-2, -4],[0, -4],[1, -4],[2, -4],[0, -4],[-1, -4],[-2, -4],[-3, -4],[-3, -6],[-2, -7]]], "estimated_rewards": [ -87, -91.1111, -90.1639, -86.9347, -80, -76.2887, -85.1064, -82.2222, -78.8235, -81.7143, -74.1573, -80.3279, -70.1031, -72.7749, -56.4246, -88.0435, -62.6374, 40, 11.9171, -41.8605]},{ "winner": 0, "length": 30, "reward": 100, "trajectories": [[[0, 7],[-1, 7],[-2, 7],[-3, 7],[-3, 6],[-3, 5],[-3, 4],[-3, 3],[-3, 2],[-3, 1],[-3, 0],[-3, -1],[-4, -1],[-4, -2],[-4, -3],[-4, -2],[-4, -1],[-4, 0],[-3, 0],[-3, -1],[-4, -1],[-4, -2],[-4, -3],[-4, -4],[-4, -5],[-4, -6],[-4, -7],[-3, -7],[-2, -7],[-1, -7],[0, -7]],[[6, 2],[5, 2],[5, 1],[5, -1],[5, -2],[5, -1],[5, -2],[5, -3],[6, -4],[5, -4],[3, -4],[2, -4],[0, -4],[-1, -4],[-2, -4],[-3, -4],[-5, -4],[-4, -3],[-3, -4],[-1, -4],[0, -4],[1, -4],[2, -4],[1, -4],[-1, -4],[-3, -4],[-4, -5],[-3, -5],[-2, -5],[-1, -5],[0, -5]]], "estimated_rewards": [ -93.0348, -88.8889, -92.7835, -89.899, -82.1596, -75.5319, -77.3196, -75.4386, -74.8571, -78.1421, -77.665, -83.7563, -72.7273, -64.7059, -94.152, -94.5355, -95.4802, -97.8022, -80.4444, -86.6667, -80.7487, -88.5417, -92.2222, -91.0615, -57.0681, 42.3729, 10.4651, 55.3191, 100, 100]},{ "winner": 1, "length": 30, "reward": -100, "trajectories": [[[0, 7],[-1, 7],[-2, 7],[-3, 7],[-3, 6],[-3, 5],[-3, 4],[-3, 3],[-3, 2],[-3, 1],[-3, 0],[-3, -1],[-4, -1],[-4, -2],[-4, -3],[-4, -2],[-4, -1],[-3, -1],[-4, -1],[-3, -1],[-4, -1],[-4, -2],[-4, -3],[-4, -2],[-4, -3],[-4, -4],[-4, -5],[-4, -6],[-4, -7],[-3, -7],[-2, -7]],[[6, 2],[5, 2],[5, 0],[5, -1],[4, -2],[5, -2],[5, 0],[5, -1],[5, -2],[3, -2],[2, -2],[0, -2],[-1, -3],[-1, -4],[-2, -4],[-2, -5],[-3, -5],[-4, -4],[-4, -2],[-3, -3],[-2, -4],[-1, -4],[0, -4],[1, -4],[3, -4],[1, -4],[-1, -4],[-2, -4],[-3, -4],[-3, -6],[-2, -7]]], "estimated_rewards": [ -90.2439, -90.9605, -91.0615, -79.5918, -87.3684, -87.5648, -75.5814, -80, -74.1573, -69.5906, -84.7619, -74.1627, -74.0933, -48, -95.3488, -95.5157, -93.7824, -89.8305, -94.2529, -96.7391, -91.716, -74.0933, -96.7568, -71.7391, -83.3333, -87.7778, -44.1341, 44.5783, 14.2857, -45.3552]},{ "winner": 0, "length": 22, "reward": 100, "trajectories": [[[0, 7],[-1, 7],[-2, 7],[-3, 7],[-3, 6],[-3, 5],[-3, 4],[-3, 3],[-3, 2],[-3, 1],[-3, 0],[-3, -1],[-4, -1],[-4, -2],[-4, -3],[-4, -4],[-4, -5],[-4, -6],[-4, -7],[-3, -7],[-2, -7],[-1, -7],[0, -7]],[[6, 2],[5, 1],[5, -1],[5, -2],[3, -2],[2, -2],[0, -2],[-1, -3],[-2, -4],[-3, -4],[-4, -3],[-3, -4],[-2, -4],[-1, -4],[0, -4],[-1, -4],[-2, -4],[-3, -4],[-4, -4],[-3, -5],[-2, -6],[-1, -6],[0, -6]]], "estimated_rewards": [ -83.0846, -86.5285, -86.1272, -90.7692, -83.5749, -80.7487, -79.5699, -75.2809, -74.0541, -66.8342, -72.4138, -86.0697, -73.6527, -41.4634, -44.2105, -96.5909, -50, 34.4262, 80.8511, 57.6087, 18.3908, 100]},{ "winner": 1, "length": 18, "reward": -100, "trajectories": [[[0, 7],[-1, 7],[-2, 7],[-2, 6],[-3, 6],[-3, 5],[-3, 4],[-3, 3],[-3, 2],[-3, 1],[-3, 0],[-3, -1],[-4, -1],[-3, -1],[-4, -1],[-4, -2],[-4, -1],[-3, -1],[-4, -1]],[[6, 2],[5, 2],[5, 1],[5, -1],[4, -2],[5, -2],[3, -2],[1, -2],[0, -2],[-1, -3],[-2, -4],[-4, -4],[-4, -3],[-3, -3],[-3, -4],[-4, -4],[-4, -3],[-4, -1],[-4, -1]]], "estimated_rewards": [ -95.6284, -91.8367, -86.5854, -86.7299, -84.456, -84.2365, -85.3403, -67.3469, -76.4045, -72.3757, -79.8742, -81.4815, -96.0199, -81.8182, -92.5532, -94.7644, -95.7895, -100]},{ "winner": 0, "length": 22, "reward": 100, "trajectories": [[[0, 7],[-1, 7],[-2, 7],[-3, 7],[-3, 6],[-3, 5],[-3, 4],[-3, 3],[-3, 2],[-3, 1],[-3, 0],[-3, -1],[-4, -1],[-4, -2],[-4, -3],[-4, -4],[-4, -5],[-4, -6],[-4, -7],[-3, -7],[-2, -7],[-1, -7],[0, -7]],[[6, 2],[5, 1],[5, 0],[5, -2],[3, -2],[1, -2],[0, -2],[-1, -2],[-1, -4],[-3, -4],[-4, -4],[-2, -4],[-1, -4],[0, -4],[2, -4],[1, -4],[0, -4],[-1, -4],[-2, -4],[-3, -4],[-2, -5],[-1, -5],[0, -5]]], "estimated_rewards": [ -88.5057, -87.1345, -93.4066, -88.0435, -82.7273, -82.8283, -77.665, -76.5957, -78.2383, -74.3017, -79.0698, -81.7204, -71.9512, -69.4737, -47.027, -87.1658, -23.6181, 37.6344, 82.0513, 100, 100, 100]},{ "winner": 1, "length": 23, "reward": -100, "trajectories": [[[0, 7],[-1, 7],[-2, 7],[-3, 7],[-4, 7],[-4, 6],[-4, 5],[-4, 4],[-4, 3],[-4, 2],[-4, 1],[-3, 1],[-3, 0],[-3, -1],[-4, -1],[-4, -2],[-4, -3],[-4, -4],[-4, -5],[-4, -6],[-4, -7],[-3, -7],[-2, -7],[-1, -7]],[[6, 2],[5, 1],[5, 0],[5, -1],[4, -2],[2, -2],[0, -2],[-1, -3],[-1, -4],[-2, -4],[-4, -4],[-4, -3],[-4, -2],[-3, -3],[-2, -4],[-1, -4],[1, -4],[0, -4],[-1, -4],[-3, -4],[-4, -4],[-3, -5],[-2, -6],[-1, -7]]], "estimated_rewards": [ -90.2439, -90.566, -88.7755, -85.1852, -79.5918, -85.4545, -80.5405, -84.8485, -77, -67.5393, -96.0396, -79.6954, -94.2029, -94.8454, -89.0547, -82.7411, -92.6829, -93.8272, -61.4973, 46.3918, 81.7259, 61.8497, 10.2703]},{ "winner": 0, "length": 26, "reward": 100, "trajectories": [[[0, 7],[-1, 7],[-2, 7],[-3, 7],[-3, 6],[-3, 5],[-3, 4],[-3, 3],[-3, 2],[-3, 1],[-3, 0],[-3, -1],[-4, -1],[-3, -1],[-3, 0],[-3, -1],[-4, -1],[-4, -2],[-4, -3],[-4, -4],[-4, -5],[-4, -6],[-4, -7],[-3, -7],[-2, -7],[-1, -7],[0, -7]],[[6, 2],[5, 1],[5, -1],[5, -2],[4, -2],[3, -2],[1, -2],[0, -2],[-1, -3],[-2, -4],[-3, -4],[-4, -3],[-4, -2],[-3, -3],[-3, -4],[-2, -4],[-1, -3],[0, -3],[-1, -4],[-2, -4],[-3, -4],[-4, -4],[-5, -4],[-3, -4],[-2, -5],[-1, -5],[0, -6]]], "estimated_rewards": [ -91.6667, -93.3333, -90.4762, -79.1469, -81.3187, -79.798, -74.7475, -85.1852, -68.75, -73.8095, -71.0983, -82.2222, -94.3503, -96.2085, -76.2712, -90, -87.8788, -77.2277, -89.3048, -96.25, -65.9794, -26.8817, 100, 100, 100, 100]},{ "winner": 1, "length": 12, "reward": -100, "trajectories": [[[0, 7],[-1, 7],[-2, 7],[-3, 7],[-3, 6],[-3, 5],[-3, 4],[-3, 3],[-3, 2],[-3, 1],[-3, 0],[-3, -1],[-4, -1]],[[6, 2],[5, 1],[5, 0],[5, -1],[4, -2],[2, -2],[0, -2],[-1, -2],[-1, -3],[-2, -4],[-3, -4],[-4, -3],[-4, -1]]], "estimated_rewards": [ -85.567, -86.8132, -90.2174, -80.5714, -81.25, -84.8485, -65.3179, -75.2688, -69.1489, -69.5431, -72.7273, -76.8889]},{ "winner": 1, "length": 14, "reward": -100, "trajectories": [[[0, 7],[-1, 7],[-2, 7],[-3, 7],[-3, 6],[-3, 5],[-3, 4],[-3, 3],[-3, 2],[-3, 1],[-3, 0],[-3, -1],[-4, -1],[-3, -1],[-4, -1]],[[6, 2],[5, 1],[5, -1],[5, -2],[4, -2],[2, -2],[1, -2],[0, -2],[-1, -2],[-1, -4],[-3, -4],[-4, -4],[-4, -3],[-4, -2],[-4, -1]]], "estimated_rewards": [ -90.5172, -90.3226, -87.3016, -82.0896, -77.2277, -82.8877, -87.8453, -83.815, -68.6869, -74.0541, -77.3196, -77.6471, -97.5904, -90.7834]},{ "winner": 1, "length": 24, "reward": -100, "trajectories": [[[0, 7],[-1, 7],[-2, 7],[-3, 7],[-3, 6],[-3, 5],[-3, 4],[-3, 3],[-3, 2],[-3, 1],[-3, 0],[-3, -1],[-4, -1],[-4, -2],[-4, -3],[-4, -4],[-4, -3],[-4, -2],[-4, -1],[-3, -1],[-3, 0],[-3, -1],[-4, -1],[-3, -1],[-4, -1]],[[6, 2],[5, 1],[5, -1],[4, -2],[3, -2],[2, -2],[1, -2],[0, -2],[-1, -3],[-1, -4],[-3, -4],[-2, -4],[-1, -4],[0, -4],[1, -4],[-1, -4],[-2, -4],[-4, -4],[-4, -2],[-4, -3],[-3, -4],[-2, -4],[-4, -4],[-4, -2],[-4, -1]]], "estimated_rewards": [ -89.8305, -88.172, -91.0448, -90.0552, -83.2402, -83.6066, -78, -75.3086, -72.3757, -79.2079, -77.551, -76, -75.1244, -61.194, -50.2959, -93.8462, -96.9849, -95.7672, -92.8571, -95.0311, -81.0945, -80.9524, -94.382, -84.9711]},{ "winner": 1, "length": 18, "reward": -100, "trajectories": [[[0, 7],[-1, 7],[-2, 7],[-2, 6],[-3, 6],[-3, 5],[-3, 4],[-3, 3],[-3, 2],[-3, 1],[-3, 0],[-3, -1],[-4, -1],[-3, -1],[-4, -1],[-3, -1],[-4, -1],[-4, -2],[-4, -3]],[[6, 2],[5, 2],[5, 1],[5, -1],[5, -2],[3, -2],[2, -2],[0, -2],[-1, -3],[-1, -4],[-3, -4],[-4, -4],[-5, -4],[-4, -4],[-4, -3],[-3, -3],[-3, -4],[-4, -3],[-4, -3]]], "estimated_rewards": [ -89.7196, -90.8629, -89.8477, -96.1722, -86.2069, -83.2512, -78.022, -79.5918, -75.2688, -67.9012, -79.798, -78.8018, -94.4444, -91.3978, -96.6851, -88.7179, -87.1287, -98.9637]},{ "winner": 1, "length": 12, "reward": -100, "trajectories": [[[0, 7],[-1, 7],[-2, 7],[-3, 7],[-3, 6],[-3, 5],[-3, 4],[-3, 3],[-3, 2],[-3, 1],[-3, 0],[-3, -1],[-4, -1]],[[6, 2],[5, 1],[5, -1],[4, -2],[2, -2],[1, -2],[-1, -2],[-1, -4],[-3, -4],[-4, -4],[-4, -3],[-4, -2],[-4, -1]]], "estimated_rewards": [ -92.3497, -93.0636, -87.7778, -85.8586, -86.2857, -77.9904, -88.5714, -76, -84.4444, -72.8643, -65.9794, -80.1105]},{ "winner": 1, "length": 14, "reward": -100, "trajectories": [[[0, 7],[-1, 7],[-2, 7],[-3, 7],[-3, 6],[-3, 5],[-3, 4],[-3, 3],[-3, 2],[-3, 1],[-3, 0],[-3, -1],[-4, -1],[-3, -1],[-4, -1]],[[6, 2],[5, 2],[5, 1],[5, 0],[5, -1],[4, -2],[2, -2],[1, -2],[-1, -2],[-1, -4],[-2, -4],[-3, -4],[-4, -3],[-4, -2],[-4, -1]]], "estimated_rewards": [ -85.3403, -91.1602, -87.9781, -91.8367, -87.9121, -89.4737, -79.5699, -76.3158, -80.8511, -73.4807, -71.7073, -79.6296, -94.4134, -84]},{ "winner": 1, "length": 16, "reward": -100, "trajectories": [[[0, 7],[-1, 7],[-2, 7],[-3, 7],[-3, 6],[-3, 5],[-3, 4],[-3, 3],[-3, 2],[-3, 1],[-3, 0],[-3, -1],[-4, -1],[-4, -2],[-4, -3],[-4, -2],[-4, -1]],[[6, 2],[7, 2],[6, 2],[5, 2],[5, 0],[5, -1],[5, -2],[4, -2],[3, -2],[2, -2],[0, -2],[-1, -2],[-1, -4],[-2, -4],[-3, -4],[-4, -3],[-4, -1]]], "estimated_rewards": [ -88.3598, -94, -93.1707, -80.198, -88.8325, -84.6154, -85.1429, -76.0417, -75.2809, -77.2455, -76.2376, -81.4634, -75.5556, -57.2093, -96.6667, -96.1353]},{ "winner": 0, "length": 22, "reward": 100, "trajectories": [[[0, 7],[-1, 7],[-2, 7],[-3, 7],[-3, 6],[-3, 5],[-3, 4],[-3, 3],[-3, 2],[-3, 1],[-3, 0],[-3, -1],[-4, -1],[-4, -2],[-4, -3],[-4, -4],[-4, -5],[-4, -6],[-4, -7],[-3, -7],[-2, -7],[-1, -7],[0, -7]],[[6, 2],[5, 1],[5, -1],[4, -2],[3, -2],[2, -2],[1, -2],[-1, -2],[-1, -3],[-2, -4],[-1, -4],[1, -4],[3, -4],[5, -4],[3, -4],[2, -4],[0, -4],[-2, -4],[-3, -4],[-3, -6],[-2, -6],[-1, -6],[0, -6]]], "estimated_rewards": [ -92.233, -92.1348, -94.5055, -84.6154, -90.9091, -82.2917, -76, -76.8421, -65.1282, -84.3373, -80.8219, -76.8421, -70.6161, -63.285, -50, -85.7143, -37.234, 39.0374, 14.5833, -43.1579, 12.9534, 100]},{ "winner": 1, "length": 16, "reward": -100, "trajectories": [[[0, 7],[-1, 7],[-2, 7],[-3, 7],[-3, 6],[-3, 5],[-3, 4],[-3, 3],[-3, 2],[-3, 1],[-3, 0],[-3, -1],[-4, -1],[-3, -1],[-4, -1],[-4, -2],[-4, -1]],[[6, 2],[5, 1],[5, 0],[5, -2],[4, -2],[2, -2],[1, -2],[0, -2],[-1, -3],[-1, -4],[-2, -4],[-4, -4],[-4, -3],[-3, -3],[-3, -4],[-4, -3],[-4, -1]]], "estimated_rewards": [ -89.1892, -89.1403, -93.1818, -83.5443, -90.8046, -85.7143, -81.5789, -71.4286, -75, -74.4681, -74.3017, -73.3333, -97.0874, -83.2512, -93.4641, -95.122]},{ "winner": 0, "length": 34, "reward": 100, "trajectories": [[[0, 7],[-1, 7],[-2, 7],[-3, 7],[-3, 6],[-3, 5],[-3, 4],[-3, 3],[-3, 2],[-3, 1],[-3, 0],[-3, -1],[-4, -1],[-4, 0],[-4, 1],[-3, 1],[-3, 0],[-3, 1],[-2, 1],[-1, 1],[-2, 1],[-3, 1],[-3, 0],[-3, -1],[-4, -1],[-4, -2],[-4, -3],[-4, -4],[-4, -5],[-4, -6],[-4, -7],[-3, -7],[-2, -7],[-1, -7],[0, -7]],[[6, 2],[5, 1],[5, 0],[5, -1],[4, -2],[3, -2],[1, -2],[0, -2],[-1, -2],[-1, -3],[-2, -4],[-2, -5],[-3, -5],[-4, -5],[-4, -4],[-4, -3],[-4, -2],[-4, -1],[-4, -3],[-3, -3],[-2, -4],[-1, -4],[0, -4],[2, -4],[4, -4],[5, -4],[5, -3],[4, -3],[3, -3],[1, -3],[-1, -3],[-1, -4],[-2, -4],[-1, -5],[0, -6]]], "estimated_rewards": [ -93.3962, -95.2381, -84.0909, -84.6154, -85.5422, -79.0576, -76.7196, -76.9231, -77.5148, -74.6032, -70.5584, -78.3019, -95.6044, -96.3415, -95.8115, -82.7411, -96.6851, -97.8142, -90.8571, -96.7161, -66.2921, -79.8817, -81.1765, -70.5882, -71.875, -60.9467, -62.766, -44.5652, 20.4188, 91.5152, 83.5294, 100, 100, 100]},{ "winner": 0, "length": 24, "reward": 100, "trajectories": [[[0, 7],[-1, 7],[-2, 7],[-3, 7],[-3, 6],[-3, 5],[-3, 4],[-3, 3],[-3, 2],[-3, 1],[-3, 0],[-3, -1],[-4, -1],[-4, -2],[-4, -3],[-4, -2],[-4, -3],[-4, -4],[-4, -5],[-4, -6],[-4, -7],[-3, -7],[-2, -7],[-1, -7],[0, -7]],[[6, 2],[5, 2],[5, 0],[5, -2],[3, -2],[1, -2],[-1, -2],[-1, -4],[-3, -4],[-4, -4],[-4, -2],[-3, -3],[-2, -4],[0, -4],[2, -4],[4, -4],[5, -3],[4, -3],[2, -3],[1, -3],[0, -3],[-1, -3],[-1, -4],[-1, -6],[0, -7]]], "estimated_rewards": [ -80.8989, -88.9447, -92.9825, -82.1429, -84.2365, -85.8586, -84.1584, -75.3846, -70.6215, -69.2308, -95.283, -92.053, -91.8782, -91.4439, -96.5714, -82.7586, -75.2577, -33.7079, -2.80374, 84.8649, 100, 100, 100, 100]},{ "winner": 0, "length": 34, "reward": 100, "trajectories": [[[0, 7],[-1, 7],[-2, 7],[-2, 6],[-3, 6],[-3, 5],[-3, 4],[-3, 3],[-3, 2],[-3, 1],[-3, 0],[-3, -1],[-4, -1],[-3, -1],[-4, -1],[-4, -2],[-4, -3],[-4, -4],[-4, -3],[-4, -2],[-4, -1],[-3, -1],[-3, 0],[-3, -1],[-4, -1],[-4, -2],[-4, -3],[-4, -4],[-4, -5],[-4, -6],[-4, -7],[-3, -7],[-2, -7],[-1, -7],[0, -7]],[[6, 2],[5, 1],[5, 0],[5, -1],[5, -2],[3, -2],[2, -2],[0, -2],[-1, -2],[-1, -4],[-2, -4],[-4, -4],[-4, -3],[-3, -4],[-2, -4],[0, -4],[1, -4],[-1, -4],[-3, -4],[-4, -3],[-4, -2],[-4, -3],[-3, -3],[-3, -4],[-2, -4],[-1, -4],[1, -4],[-1, -4],[-2, -4],[-4, -4],[-4, -5],[-3, -5],[-2, -5],[-1, -5],[0, -5]]], "estimated_rewards": [ -91.4634, -89.5349, -93.6937, -91.4894, -82.199, -88.764, -75, -74.269, -68.0412, -69.0476, -72.2772, -78.6408, -97.5758, -76.6082, -85.2632, -79.6296, -94.4444, -95.7219, -96.8912, -97.7901, -97.7778, -94.6809, -82.2917, -84.0708, -76.2376, -83.4254, -83.4197, -94.7917, -53.125, -35.9116, 5.75916, 61.2245, 100, 100]},{ "winner": 0, "length": 32, "reward": 100, "trajectories": [[[0, 7],[-1, 7],[-2, 7],[-3, 7],[-3, 6],[-3, 5],[-3, 4],[-3, 3],[-3, 2],[-3, 1],[-3, 0],[-3, -1],[-4, -1],[-4, -2],[-4, -3],[-4, -2],[-4, -1],[-4, 0],[-3, 0],[-3, -1],[-3, 0],[-3, -1],[-4, -1],[-4, -2],[-4, -3],[-4, -4],[-4, -5],[-4, -6],[-4, -7],[-3, -7],[-2, -7],[-1, -7],[0, -7]],[[6, 2],[5, 1],[5, -1],[5, -2],[5, 0],[5, -1],[5, -2],[3, -2],[2, -2],[0, -2],[1, -2],[0, -2],[-1, -2],[-1, -4],[-2, -4],[-3, -4],[-5, -4],[-4, -4],[-4, -2],[-3, -3],[-3, -4],[-2, -4],[-1, -4],[0, -4],[1, -4],[-1, -4],[-2, -4],[-4, -4],[-4, -5],[-3, -5],[-2, -6],[-1, -6],[0, -7]]], "estimated_rewards": [ -91.8367, -90.5759, -89.1892, -77.7778, -80, -84.466, -76.3441, -82.6087, -72.5275, -72.7273, -77.8947, -71.875, -72.4138, -70.0483, -92.6702, -93.0636, -94.0594, -96.6292, -94.1176, -94.012, -77.8947, -78.2857, -87.9518, -84.0426, -79.0576, -97.9381, -58.8571, -43.9153, 14.7368, 56.4706, 10, 100]},{ "winner": 0, "length": 22, "reward": 100, "trajectories": [[[0, 7],[-1, 7],[-2, 7],[-3, 7],[-3, 6],[-3, 5],[-3, 4],[-3, 3],[-3, 2],[-3, 1],[-3, 0],[-3, -1],[-4, -1],[-4, -2],[-4, -3],[-4, -4],[-4, -5],[-4, -6],[-4, -7],[-3, -7],[-2, -7],[-1, -7],[0, -7]],[[6, 2],[5, 2],[5, 1],[5, -1],[5, -2],[3, -2],[1, -2],[-1, -2],[-1, -3],[-2, -4],[-4, -4],[-2, -4],[0, -4],[1, -4],[3, -4],[1, -4],[0, -4],[-2, -4],[-3, -4],[-3, -5],[-2, -6],[-1, -6],[0, -7]]], "estimated_rewards": [ -88.6598, -91.5789, -89.6907, -82.199, -90.2913, -83.8863, -84.7953, -76.5363, -73.5632, -81.9149, -72.043, -76.6667, -73.4807, -67.5127, -49.1892, -89.1156, -44.1624, 31.677, 11.6751, 56.4767, 13.7441, 100]},{ "winner": 0, "length": 26, "reward": 100, "trajectories": [[[0, 7],[-1, 7],[-2, 7],[-3, 7],[-3, 6],[-3, 5],[-3, 4],[-3, 3],[-3, 2],[-3, 1],[-3, 0],[-3, -1],[-4, -1],[-3, -1],[-4, -1],[-4, -2],[-4, -3],[-4, -2],[-4, -3],[-4, -4],[-4, -5],[-4, -6],[-4, -7],[-3, -7],[-2, -7],[-1, -7],[0, -7]],[[6, 2],[5, 2],[5, 1],[5, -1],[4, -2],[3, -2],[1, -2],[0, -2],[-1, -2],[-1, -3],[-1, -4],[-3, -4],[-4, -3],[-3, -4],[-2, -4],[0, -4],[2, -4],[4, -4],[5, -3],[3, -3],[2, -3],[0, -3],[-1, -4],[-3, -4],[-2, -4],[-1, -5],[0, -6]]], "estimated_rewards": [ -87.7551, -93.0233, -85.6287, -78.744, -85.2217, -82.0755, -82.3529, -74.8634, -76.4706, -77.3399, -78.3019, -78.1421, -95.8549, -83.8384, -87.234, -76, -93.75, -79.0576, -81.7259, -41.3613, 14.4509, 76.5957, 82.1053, 100, 100, 100]},{ "winner": 0, "length": 22, "reward": 100, "trajectories": [[[0, 7],[-1, 7],[-2, 7],[-3, 7],[-3, 6],[-3, 5],[-3, 4],[-3, 3],[-3, 2],[-3, 1],[-3, 0],[-3, -1],[-4, -1],[-4, -2],[-4, -3],[-4, -4],[-4, -5],[-4, -6],[-4, -7],[-3, -7],[-2, -7],[-1, -7],[0, -7]],[[6, 2],[5, 1],[5, 0],[5, -2],[5, 0],[5, 2],[5, 1],[5, 0],[5, -1],[5, -2],[5, 0],[5, -2],[4, -2],[3, -2],[2, -2],[0, -2],[-1, -2],[-1, -3],[-1, -4],[-3, -4],[-2, -5],[-1, -5],[0, -6]]], "estimated_rewards": [ -92.3445, -86.2069, -92.2652, -81.7259, -73.7705, -81.3472, -70.5882, -74.7573, -74.8571, -70.5263, -72.2772, -76.2162, -75.419, -63.5417, -44.6328, 6.31579, 43.8202, 91.6667, 87.7778, 100, 100, 100]},{ "winner": 1, "length": 21, "reward": -100, "trajectories": [[[0, 7],[-1, 7],[-2, 7],[-3, 7],[-3, 6],[-3, 5],[-3, 4],[-3, 3],[-3, 2],[-3, 1],[-3, 0],[-3, -1],[-4, -1],[-4, -2],[-4, -3],[-4, -4],[-4, -5],[-4, -6],[-4, -7],[-3, -7],[-2, -7],[-1, -7]],[[6, 2],[5, 1],[5, -1],[4, -2],[2, -2],[1, -2],[0, -2],[-1, -2],[-1, -4],[-3, -4],[-4, -4],[-3, -4],[-1, -4],[1, -4],[3, -4],[2, -4],[1, -4],[-1, -4],[-2, -4],[-3, -5],[-2, -6],[-1, -7]]], "estimated_rewards": [ -92.7461, -78.6517, -92.233, -81.6216, -72.3404, -70.8543, -74.7368, -68.4783, -75.9615, -73.0337, -71.875, -80.3922, -73.4043, -71.4286, -53.6842, -81.1765, -42.6901, 52, 77.2455, 55.2448, 10.4972]},{ "winner": 1, "length": 12, "reward": -100, "trajectories": [[[0, 7],[-1, 7],[-2, 7],[-3, 7],[-3, 6],[-3, 5],[-3, 4],[-3, 3],[-3, 2],[-3, 1],[-3, 0],[-3, -1],[-4, -1]],[[6, 2],[5, 2],[5, 0],[5, -2],[3, -2],[1, -2],[-1, -2],[-1, -4],[-2, -4],[-3, -4],[-4, -3],[-4, -2],[-4, -1]]], "estimated_rewards": [ -89.1892, -92.9293, -93.0636, -86.7347, -81.2808, -80.4348, -83.6957, -75.419, -83.0303, -72.2543, -67.2316, -71.134]},{ "winner": 1, "length": 23, "reward": -100, "trajectories": [[[0, 7],[-1, 7],[-2, 7],[-3, 7],[-3, 6],[-3, 5],[-3, 4],[-3, 3],[-3, 2],[-3, 1],[-3, 0],[-3, -1],[-4, -1],[-3, -1],[-4, -1],[-4, -2],[-4, -3],[-4, -4],[-4, -5],[-4, -6],[-4, -7],[-3, -7],[-2, -7],[-1, -7]],[[6, 2],[5, 2],[5, 1],[5, 0],[5, -1],[4, -2],[3, -2],[2, -2],[0, -2],[-1, -2],[-1, -3],[-2, -4],[-4, -4],[-2, -4],[-1, -4],[0, -4],[1, -4],[0, -4],[-2, -4],[-4, -4],[-4, -5],[-3, -5],[-2, -6],[-1, -7]]], "estimated_rewards": [ -89.011, -91.716, -90.1099, -88.4615, -87.6923, -83.6538, -79.3814, -78.3251, -73.057, -72.067, -74.1294, -85.6459, -93.5829, -81, -85.7988, -80.2198, -92.5532, -93.8462, -56.9892, -32.1637, 10.6383, 60, 1.7341]},{ "winner": 1, "length": 23, "reward": -100, "trajectories": [[[0, 7],[-1, 7],[-2, 7],[-3, 7],[-3, 6],[-3, 5],[-3, 4],[-3, 3],[-3, 2],[-3, 1],[-3, 0],[-3, -1],[-4, -1],[-3, -1],[-4, -1],[-4, 0],[-3, 0],[-3, -1],[-4, -1],[-4, -2],[-4, -1],[-4, 0],[-4, 1],[-4, 0]],[[6, 2],[5, 1],[5, -1],[5, -2],[4, -2],[3, -2],[1, -2],[0, -2],[-1, -2],[-1, -3],[-1, -4],[-3, -4],[-4, -3],[-3, -4],[-4, -4],[-4, -3],[-3, -4],[-2, -4],[-1, -4],[-3, -4],[-5, -4],[-4, -3],[-4, -1],[-4, 0]]], "estimated_rewards": [ -89, -93.1373, -86.6667, -87.8788, -82.1229, -80.8219, -78.4946, -80.9524, -71.0692, -82.8877, -79.5455, -79.4872, -91.6667, -89.9497, -96.7213, -97.9275, -77.2021, -76.4103, -82.0225, -91.4894, -95.2941, -96.7742, -100]}]