[{ "code": 1, "length": 14, "reward": 100, "trajectories": [[[0, 7],[0, 6],[0, 5],[0, 4],[0, 3],[0, 2],[0, 1],[0, 0],[0, -1],[0, -2],[0, -3],[0, -4],[0, -5],[0, -6],[0, -7]],[[7, 1],[7, 3],[7, 5],[5, 5],[4, 5],[3, 5],[2, 5],[0, 5],[0, 4],[0, 3],[0, 1],[0, 0],[0, -2],[0, -4],[0, -5]]], "estimated_rewards": [ -47.8261, -48.9362, 65.0602, 70.0787, 67.8832, 67.6923, 95.122, 79.1045, 94.8387, 100, 100, 100, 100, 100]},{ "code": 1, "length": 14, "reward": 100, "trajectories": [[[0, 7],[0, 6],[0, 5],[0, 4],[0, 3],[0, 2],[0, 1],[0, 0],[0, -1],[0, -2],[0, -3],[0, -4],[0, -5],[0, -6],[0, -7]],[[7, 1],[7, 2],[7, 3],[7, 4],[6, 5],[4, 5],[3, 5],[1, 5],[0, 5],[0, 3],[0, 2],[0, 1],[0, 0],[0, -2],[0, -3]]], "estimated_rewards": [ -55.5556, -46.0317, -32.1212, -6.76692, 16.5354, 37.8378, 49.2063, 97.2973, 100, 100, 100, 100, 100, 100]},{ "code": 1, "length": 14, "reward": 100, "trajectories": [[[0, 7],[0, 6],[0, 5],[0, 4],[0, 3],[0, 2],[0, 1],[0, 0],[0, -1],[0, -2],[0, -3],[0, -4],[0, -5],[0, -6],[0, -7]],[[7, 1],[6, 0],[7, 1],[7, 3],[7, 4],[7, 5],[5, 5],[3, 5],[2, 5],[1, 5],[0, 5],[0, 3],[0, 2],[0, 1],[0, -1]]], "estimated_rewards": [ -45.0704, -31.4286, -46.3087, -0.636943, 17.3333, 44.8276, 50, 79.7101, 100, 100, 100, 100, 100, 100]},{ "code": 0, "length": 12, "reward": -100, "trajectories": [[[0, 7],[0, 6],[0, 5],[0, 4],[0, 3],[0, 2],[0, 1],[0, 0],[0, -1],[0, -2],[0, -3],[0, -4],[0, -5]],[[7, 1],[7, 2],[7, 4],[6, 5],[4, 5],[2, 5],[0, 5],[0, 3],[0, 2],[0, 1],[0, -1],[0, -3],[0, -5]]], "estimated_rewards": [ -47.2868, -30.4965, -42.2819, -15.3285, 25, 34.5912, 11.2676, -15.7143, 14.0741, 52.6316, 24.1935, -38.5621]},{ "code": 1, "length": 14, "reward": 100, "trajectories": [[[0, 7],[0, 6],[0, 5],[0, 4],[0, 3],[0, 2],[0, 1],[0, 0],[0, -1],[0, -2],[0, -3],[0, -4],[0, -5],[0, -6],[0, -7]],[[7, 1],[7, 2],[7, 4],[7, 5],[6, 5],[5, 5],[3, 5],[2, 5],[1, 4],[0, 3],[0, 2],[0, 1],[0, 0],[0, -2],[0, -3]]], "estimated_rewards": [ -61.25, -43.662, -43.0556, -3.64964, 7.24638, 48.4663, 47.7612, 75.9398, 100, 100, 100, 100, 100, 100]},{ "code": 1, "length": 14, "reward": 100, "trajectories": [[[0, 7],[0, 6],[0, 5],[0, 4],[0, 3],[0, 2],[0, 1],[0, 0],[0, -1],[0, -2],[0, -3],[0, -4],[0, -5],[0, -6],[0, -7]],[[7, 1],[7, 3],[7, 5],[6, 5],[4, 5],[3, 5],[2, 5],[1, 5],[0, 5],[0, 4],[0, 3],[0, 2],[0, 1],[0, 0],[0, -1]]], "estimated_rewards": [ -59.7403, -35.5263, 56.9231, 70.8609, 67.1642, 65.6716, 93.2203, 97.561, 100, 100, 100, 100, 100, 100]},{ "code": 1, "length": 14, "reward": 100, "trajectories": [[[0, 7],[0, 6],[0, 5],[0, 4],[0, 3],[0, 2],[0, 1],[0, 0],[0, -1],[0, -2],[0, -3],[0, -4],[0, -5],[0, -6],[0, -7]],[[7, 1],[7, 2],[7, 3],[7, 5],[5, 5],[4, 5],[3, 5],[2, 5],[1, 5],[0, 4],[0, 2],[0, 1],[0, -1],[0, -2],[0, -4]]], "estimated_rewards": [ -59.1549, -36.6197, -35.5932, -12.8571, 16.9811, 32.3944, 56.7164, 78.2051, 100, 100, 100, 100, 100, 100]},{ "code": 1, "length": 14, "reward": 100, "trajectories": [[[0, 7],[0, 6],[0, 5],[0, 4],[0, 3],[0, 2],[0, 1],[0, 0],[0, -1],[0, -2],[0, -3],[0, -4],[0, -5],[0, -6],[0, -7]],[[7, 1],[7, 2],[7, 3],[7, 4],[7, 5],[6, 5],[5, 5],[4, 5],[3, 5],[2, 5],[1, 5],[0, 5],[0, 3],[0, 1],[0, -1]]], "estimated_rewards": [ -47.4453, -42.515, -23.8806, -9.48905, 1.96078, 51.5924, 45.5882, 88.1356, 100, 100, 100, 100, 100, 100]},{ "code": 1, "length": 14, "reward": 100, "trajectories": [[[0, 7],[0, 6],[0, 5],[0, 4],[0, 3],[0, 2],[0, 1],[0, 0],[0, -1],[0, -2],[0, -3],[0, -4],[0, -5],[0, -6],[0, -7]],[[7, 1],[7, 2],[7, 3],[7, 4],[6, 5],[5, 5],[4, 5],[3, 5],[2, 5],[1, 5],[0, 5],[0, 4],[0, 2],[0, 1],[0, 0]]], "estimated_rewards": [ -43.0464, -40.2778, -33.3333, -7.38255, 19.2053, 46.3415, 60.274, 90.0709, 98.6207, 100, 100, 100, 100, 100]},{ "code": 1, "length": 14, "reward": 100, "trajectories": [[[0, 7],[0, 6],[0, 5],[0, 4],[0, 3],[0, 2],[0, 1],[0, 0],[0, -1],[0, -2],[0, -3],[0, -4],[0, -5],[0, -6],[0, -7]],[[7, 1],[7, 3],[7, 5],[6, 5],[5, 5],[3, 5],[2, 5],[1, 4],[0, 3],[0, 1],[0, 0],[0, -2],[0, -3],[0, -4],[0, -5]]], "estimated_rewards": [ -53.6424, -38.806, 55, 63.5135, 61.7647, 67.8322, 93.8931, 84.507, 60.7843, 44.9275, 74.359, 48.1481, 100, 100]}]